rcol/__init__.py
rcol/instruments.py
rcol-0.0.2.dist-info/METADATA
rcol-0.0.2.dist-info/WHEEL
rcol-0.0.2.dist-info/top_level.txt
rcol-0.0.2.dist-info/RECORD
