Metadata-Version: 2.4
Name: rcol
Version: 0.0.2
Summary: Pandas DataFrame templates for REDCap instruments, with stacking and upload functionality.
Author-email: Julius Welzel <julius.welzel@gmail.com>
Requires-Python: >=3.8
Requires-Dist: python-dotenv
Requires-Dist: pandas>=1.5.0
Requires-Dist: PyCap>=2.0.0
Requires-Dist: ipykernel>=6.29.5
